LICENSE.txt
MANIFEST.in
README.rst
setup.py
lekt/__about__.py
lekt/__init__.py
lekt/bindmounts.py
lekt/config.py
lekt/env.py
lekt/exceptions.py
lekt/fmt.py
lekt/images.py
lekt/interactive.py
lekt/jobs.py
lekt/serialize.py
lekt/types.py
lekt/utils.py
lekt.egg-info/PKG-INFO
lekt.egg-info/SOURCES.txt
lekt.egg-info/dependency_links.txt
lekt.egg-info/entry_points.txt
lekt.egg-info/requires.txt
lekt.egg-info/top_level.txt
lekt/commands/__init__.py
lekt/commands/cli.py
lekt/commands/compose.py
lekt/commands/config.py
lekt/commands/context.py
lekt/commands/dev.py
lekt/commands/images.py
lekt/commands/k8s.py
lekt/commands/local.py
lekt/commands/plugins.py
lekt/commands/upgrade/__init__.py
lekt/commands/upgrade/common.py
lekt/commands/upgrade/k8s.py
lekt/commands/upgrade/local.py
lekt/hooks/__init__.py
lekt/hooks/actions.py
lekt/hooks/consts.py
lekt/hooks/contexts.py
lekt/hooks/filters.py
lekt/plugins/__init__.py
lekt/plugins/base.py
lekt/plugins/v0.py
lekt/plugins/v1.py
lekt/templates/kustomization.yml
lekt/templates/version
lekt/templates/apps/caddy/Caddyfile
lekt/templates/apps/openedx/config/cms.env.yml
lekt/templates/apps/openedx/config/lms.env.yml
lekt/templates/apps/openedx/config/partials/auth.yml
lekt/templates/apps/openedx/settings/cms/__init__.py
lekt/templates/apps/openedx/settings/cms/development.py
lekt/templates/apps/openedx/settings/cms/production.py
lekt/templates/apps/openedx/settings/cms/test.py
lekt/templates/apps/openedx/settings/lms/__init__.py
lekt/templates/apps/openedx/settings/lms/development.py
lekt/templates/apps/openedx/settings/lms/production.py
lekt/templates/apps/openedx/settings/lms/test.py
lekt/templates/apps/openedx/settings/partials/common_all.py
lekt/templates/apps/openedx/settings/partials/common_cms.py
lekt/templates/apps/openedx/settings/partials/common_lms.py
lekt/templates/apps/openedx/settings/partials/common_test.py
lekt/templates/apps/redis/redis.conf
lekt/templates/build/openedx/Dockerfile
lekt/templates/build/openedx/revisions.yml
lekt/templates/build/openedx/bin/openedx-assets
lekt/templates/build/openedx/bin/reload-uwsgi
lekt/templates/build/openedx/bin/site-configuration
