Metadata-Version: 2.1
Name: lekt
Version: 14.0.35
Summary: The Docker-based Open edX distribution designed for peace of mind
Home-page: https://docs.tutor.overhang.io/
Author: Overhang.io
Author-email: contact@overhang.io
License: AGPLv3
Project-URL: Code, https://github.com/lektorium-tutor/lekt
Project-URL: Issue tracker, https://github.com/lektorium-tutor/lekt/issues
Classifier: Development Status :: 5 - Production/Stable
Classifier: Intended Audience :: Developers
Classifier: License :: OSI Approved :: GNU Affero General Public License v3
Classifier: Operating System :: OS Independent
Classifier: Programming Language :: Python
Classifier: Programming Language :: Python :: 3.7
Classifier: Programming Language :: Python :: 3.8
Classifier: Programming Language :: Python :: 3.9
Classifier: Programming Language :: Python :: 3.10
Requires-Python: >=3.7
Provides-Extra: full
License-File: LICENSE.txt
